[{"confidence": "1.0000", "file_id": "0", "bbox": "50 211 328 319"}, {"confidence": "1.0000", "file_id": "1", "bbox": "60 222 393 391"}, {"confidence": "1.0000", "file_id": "2", "bbox": "64 233 399 343"}, {"confidence": "1.0000", "file_id": "3", "bbox": "111 255 447 389"}, {"confidence": "1.0000", "file_id": "4", "bbox": "115 221 446 381"}, {"confidence": "1.0000", "file_id": "5", "bbox": "8 200 323 346"}, {"confidence": "1.0000", "file_id": "6", "bbox": "97 280 374 396"}, {"confidence": "1.0000", "file_id": "7", "bbox": "98 149 440 322"}, {"confidence": "1.0000", "file_id": "8", "bbox": "47 170 445 360"}, {"confidence": "1.0000", "file_id": "9", "bbox": "124 161 441 288"}, {"confidence": "1.0000", "file_id": "10", "bbox": "108 211 433 346"}, {"confidence": "1.0000", "file_id": "11", "bbox": "72 204 400 338"}, {"confidence": "1.0000", "file_id": "12", "bbox": "104 185 439 309"}, {"confidence": "1.0000", "file_id": "13", "bbox": "76 207 347 331"}, {"confidence": "1.0000", "file_id": "14", "bbox": "85 272 445 385"}, {"confidence": "1.0000", "file_id": "15", "bbox": "139 184 447 316"}, {"confidence": "1.0000", "file_id": "16", "bbox": "46 205 352 333"}, {"confidence": "1.0000", "file_id": "17", "bbox": "77 190 328 319"}, {"confidence": "1.0000", "file_id": "18", "bbox": "109 222 433 390"}, {"confidence": "1.0000", "file_id": "19", "bbox": "117 122 443 277"}, {"confidence": "1.0000", "file_id": "20", "bbox": "51 184 374 303"}, {"confidence": "1.0000", "file_id": "21", "bbox": "24 188 298 325"}, {"confidence": "1.0000", "file_id": "22", "bbox": "19 210 382 402"}, {"confidence": "1.0000", "file_id": "23", "bbox": "83 193 420 306"}, {"confidence": "1.0000", "file_id": "24", "bbox": "13 203 357 334"}, {"confidence": "1.0000", "file_id": "25", "bbox": "154 166 437 363"}, {"confidence": "1.0000", "file_id": "26", "bbox": "157 195 438 281"}, {"confidence": "1.0000", "file_id": "27", "bbox": "141 291 424 404"}, {"confidence": "1.0000", "file_id": "28", "bbox": "3 117 447 382"}, {"confidence": "1.0000", "file_id": "29", "bbox": "0 208 437 440"}, {"confidence": "1.0000", "file_id": "30", "bbox": "134 150 444 383"}, {"confidence": "1.0000", "file_id": "31", "bbox": "19 192 373 415"}, {"confidence": "1.0000", "file_id": "32", "bbox": "14 221 379 343"}, {"confidence": "1.0000", "file_id": "33", "bbox": "54 222 338 349"}, {"confidence": "1.0000", "file_id": "34", "bbox": "190 213 447 322"}, {"confidence": "1.0000", "file_id": "35", "bbox": "76 203 414 329"}, {"confidence": "1.0000", "file_id": "36", "bbox": "41 238 447 412"}, {"confidence": "1.0000", "file_id": "37", "bbox": "80 192 447 323"}, {"confidence": "1.0000", "file_id": "38", "bbox": "132 167 441 307"}, {"confidence": "1.0000", "file_id": "39", "bbox": "133 200 411 335"}, {"confidence": "1.0000", "file_id": "40", "bbox": "56 214 435 353"}, {"confidence": "1.0000", "file_id": "41", "bbox": "53 205 367 358"}, {"confidence": "1.0000", "file_id": "42", "bbox": "86 218 402 373"}, {"confidence": "1.0000", "file_id": "43", "bbox": "80 195 447 314"}, {"confidence": "1.0000", "file_id": "44", "bbox": "62 202 409 319"}, {"confidence": "1.0000", "file_id": "45", "bbox": "139 216 447 344"}, {"confidence": "1.0000", "file_id": "46", "bbox": "138 217 398 346"}, {"confidence": "1.0000", "file_id": "47", "bbox": "208 194 447 299"}, {"confidence": "1.0000", "file_id": "48", "bbox": "58 174 447 390"}, {"confidence": "1.0000", "file_id": "49", "bbox": "63 139 446 336"}, {"confidence": "1.0000", "file_id": "50", "bbox": "77 197 391 298"}, {"confidence": "1.0000", "file_id": "51", "bbox": "125 258 447 400"}, {"confidence": "1.0000", "file_id": "52", "bbox": "128 203 404 343"}, {"confidence": "1.0000", "file_id": "53", "bbox": "121 162 412 306"}, {"confidence": "1.0000", "file_id": "54", "bbox": "19 141 358 265"}, {"confidence": "1.0000", "file_id": "55", "bbox": "49 211 383 344"}, {"confidence": "1.0000", "file_id": "56", "bbox": "11 231 342 395"}, {"confidence": "1.0000", "file_id": "57", "bbox": "99 199 443 311"}, {"confidence": "1.0000", "file_id": "58", "bbox": "74 243 389 386"}, {"confidence": "1.0000", "file_id": "59", "bbox": "47 215 306 326"}, {"confidence": "1.0000", "file_id": "60", "bbox": "83 192 383 349"}, {"confidence": "1.0000", "file_id": "61", "bbox": "107 200 405 322"}, {"confidence": "1.0000", "file_id": "63", "bbox": "117 229 424 367"}, {"confidence": "1.0000", "file_id": "65", "bbox": "78 242 369 385"}, {"confidence": "1.0000", "file_id": "66", "bbox": "73 191 394 324"}, {"confidence": "1.0000", "file_id": "67", "bbox": "35 181 385 326"}, {"confidence": "1.0000", "file_id": "68", "bbox": "85 203 381 314"}, {"confidence": "1.0000", "file_id": "69", "bbox": "98 221 439 372"}, {"confidence": "1.0000", "file_id": "70", "bbox": "162 221 447 375"}, {"confidence": "1.0000", "file_id": "71", "bbox": "116 182 441 412"}, {"confidence": "1.0000", "file_id": "72", "bbox": "22 163 339 311"}, {"confidence": "1.0000", "file_id": "73", "bbox": "127 233 441 369"}, {"confidence": "1.0000", "file_id": "74", "bbox": "57 226 370 382"}, {"confidence": "1.0000", "file_id": "75", "bbox": "37 201 384 334"}, {"confidence": "1.0000", "file_id": "76", "bbox": "126 224 415 367"}, {"confidence": "1.0000", "file_id": "77", "bbox": "84 232 374 341"}, {"confidence": "1.0000", "file_id": "78", "bbox": "104 186 389 332"}, {"confidence": "1.0000", "file_id": "79", "bbox": "14 168 426 334"}, {"confidence": "1.0000", "file_id": "80", "bbox": "93 243 447 429"}, {"confidence": "1.0000", "file_id": "81", "bbox": "121 259 390 413"}, {"confidence": "1.0000", "file_id": "82", "bbox": "82 155 447 310"}, {"confidence": "1.0000", "file_id": "83", "bbox": "97 220 369 366"}, {"confidence": "1.0000", "file_id": "84", "bbox": "80 173 389 352"}, {"confidence": "0.9998", "file_id": "62", "bbox": "111 205 325 300"}, {"confidence": "0.9998", "file_id": "64", "bbox": "79 206 393 290"}]